pymemorymodule.pyd
pymemorymodule-0.1.0.dist-info/DESCRIPTION.rst
pymemorymodule-0.1.0.dist-info/METADATA
pymemorymodule-0.1.0.dist-info/RECORD
pymemorymodule-0.1.0.dist-info/WHEEL
pymemorymodule-0.1.0.dist-info/metadata.json
pymemorymodule-0.1.0.dist-info/top_level.txt
