Metadata-Version: 2.0
Name: pymemorymodule
Version: 0.1.0
Summary: PyMemoryModule is a Python binding for MemoryModule.
Home-page: https://bitbucket.org/sakurai_youhei/pymemorymodule/overview
Author: Youhei Sakurai
Author-email: sakurai.youhei@gmail.com
License: MPL2.0
Keywords: MemoryModule,DLL,Windows
Platform: UNKNOWN
Classifier: License :: OSI Approved :: Mozilla Public License 2.0 (MPL 2.0)
Classifier: Development Status :: 3 - Alpha
Classifier: Environment :: Win32 (MS Windows)
Classifier: Programming Language :: C
Classifier: Programming Language :: Python :: 2.6
Classifier: Programming Language :: Python :: 2.7
Classifier: Programming Language :: Python :: 3.3
Classifier: Programming Language :: Python :: 3.4
Classifier: Programming Language :: Python :: 3.5
Classifier: Operating System :: Microsoft :: Windows
Classifier: Intended Audience :: Developers
